{"nodes": [{"id": "revokemint_page", "label": "Revoke Mint Authority Tool Page", "file_type": "code", "source_file": "app/tools/revoke-mint/page.tsx", "source_location": null, "source_url": null, "captured_at": null, "author": null, "contributor": null}], "edges": [{"source": "revokemint_page", "target": "api_check_authority", "relation": "calls", "confidence": "EXTRACTED", "confidence_score": 1.0, "source_file": "app/tools/revoke-mint/page.tsx", "source_location": null, "weight": 1.0}, {"source": "revokemint_page", "target": "api_tx_revoke", "relation": "calls", "confidence": "EXTRACTED", "confidence_score": 1.0, "source_file": "app/tools/revoke-mint/page.tsx", "source_location": null, "weight": 1.0}, {"source": "revokemint_page", "target": "api_confirm", "relation": "calls", "confidence": "EXTRACTED", "confidence_score": 1.0, "source_file": "app/tools/revoke-mint/page.tsx", "source_location": null, "weight": 1.0}, {"source": "revokemint_page", "target": "usetransaction_hook", "relation": "calls", "confidence": "EXTRACTED", "confidence_score": 1.0, "source_file": "app/tools/revoke-mint/page.tsx", "source_location": null, "weight": 1.0}, {"source": "revokemint_page", "target": "useconsentshake_hook", "relation": "calls", "confidence": "EXTRACTED", "confidence_score": 1.0, "source_file": "app/tools/revoke-mint/page.tsx", "source_location": null, "weight": 1.0}, {"source": "revokemint_page", "target": "balancecheck_component", "relation": "references", "confidence": "EXTRACTED", "confidence_score": 1.0, "source_file": "app/tools/revoke-mint/page.tsx", "source_location": null, "weight": 1.0}, {"source": "revokemint_page", "target": "revokefreeze_page", "relation": "semantically_similar_to", "confidence": "INFERRED", "confidence_score": 0.95, "source_file": "app/tools/revoke-mint/page.tsx", "source_location": null, "weight": 0.95}, {"source": "revokemint_page", "target": "revokeupdate_page", "relation": "semantically_similar_to", "confidence": "INFERRED", "confidence_score": 0.95, "source_file": "app/tools/revoke-mint/page.tsx", "source_location": null, "weight": 0.95}], "hyperedges": [{"id": "authority_revocation_tools", "label": "Authority-revocation tools (check-authority -> tx/revoke -> confirm flow)", "nodes": ["revokemint_page", "revokefreeze_page", "revokeupdate_page", "makeimmutable_page"], "relation": "implement", "confidence": "INFERRED", "confidence_score": 0.85, "source_file": "app/tools/revoke-mint/page.tsx"}]}