{"nodes": [{"id": "buildUpdateMetadata_buildUpdateMetadataTx", "label": "buildUpdateMetadataTx", "file_type": "code", "source_file": "lib/solana/buildUpdateMetadata.ts", "source_location": null, "source_url": null, "captured_at": null, "author": null, "contributor": null}], "edges": [{"source": "buildUpdateMetadata_buildUpdateMetadataTx", "target": "rpcpool_leaseRpc", "relation": "calls", "confidence": "EXTRACTED", "confidence_score": 1.0, "source_file": "lib/solana/buildUpdateMetadata.ts", "source_location": null, "weight": 1.0}, {"source": "buildUpdateMetadata_buildUpdateMetadataTx", "target": "connection_getConnection", "relation": "calls", "confidence": "EXTRACTED", "confidence_score": 1.0, "source_file": "lib/solana/buildUpdateMetadata.ts", "source_location": null, "weight": 1.0}, {"source": "buildUpdateMetadata_buildUpdateMetadataTx", "target": "umi_getUmi", "relation": "calls", "confidence": "EXTRACTED", "confidence_score": 1.0, "source_file": "lib/solana/buildUpdateMetadata.ts", "source_location": null, "weight": 1.0}, {"source": "buildUpdateMetadata_buildUpdateMetadataTx", "target": "simulate_assertSimulates", "relation": "calls", "confidence": "EXTRACTED", "confidence_score": 1.0, "source_file": "lib/solana/buildUpdateMetadata.ts", "source_location": null, "weight": 1.0}], "hyperedges": []}