{"nodes": [{"id": "Navbar_Navbar", "label": "Navbar component", "file_type": "code", "source_file": "components/Navbar.tsx", "source_location": null, "source_url": null, "captured_at": null, "author": null, "contributor": null}], "edges": [{"source": "Navbar_Navbar", "target": "MobileWalletButton_MobileWalletButton", "relation": "references", "confidence": "EXTRACTED", "confidence_score": 1.0, "source_file": "components/Navbar.tsx", "source_location": null, "weight": 1.0}, {"source": "Navbar_Navbar", "target": "mobile_isMobileBrowser", "relation": "calls", "confidence": "EXTRACTED", "confidence_score": 1.0, "source_file": "components/Navbar.tsx", "source_location": null, "weight": 1.0}], "hyperedges": []}